scripts/generate_release_notes.py
varlord/__init__.py
varlord/config.py
varlord/converters.py
varlord/exceptions.py
varlord/exporters.py
varlord/global_config.py
varlord/logging.py
varlord/metadata.py
varlord/model_validation.py
varlord/policy.py
varlord/resolver.py
varlord/source_help.py
varlord/store.py
varlord/validators.py
varlord/sources/__init__.py
varlord/sources/base.py
varlord/sources/cli.py
varlord/sources/defaults.py
varlord/sources/dotenv.py
varlord/sources/env.py
varlord/sources/etcd.py
varlord/sources/file_base.py
varlord/sources/json.py
varlord/sources/toml.py
varlord/sources/yaml.py
varlord-0.8.0.dist-info/licenses/LICENSE
varlord-0.8.0.dist-info/METADATA
varlord-0.8.0.dist-info/WHEEL
varlord-0.8.0.dist-info/top_level.txt
varlord-0.8.0.dist-info/RECORD
