Metadata-Version: 2.4
Name: varlord
Version: 0.8.0
Summary: A powerful Python configuration management library with support for defaults, CLI args, environment variables, .env files, and optional etcd integration with dynamic updates
Author: Varlord Team
License-Expression: Apache-2.0
Project-URL: Homepage, https://github.com/lzjever/varlord
Project-URL: Documentation, https://varlord.readthedocs.io
Project-URL: Repository, https://github.com/lzjever/varlord
Project-URL: Issues, https://github.com/lzjever/varlord/issues
Keywords: configuration,config,env,etcd,settings,cli-args
Classifier: Development Status :: 4 - Beta
Classifier: Intended Audience :: Developers
Classifier: Programming Language :: Python :: 3
Classifier: Programming Language :: Python :: 3.8
Classifier: Programming Language :: Python :: 3.9
Classifier: Programming Language :: Python :: 3.10
Classifier: Programming Language :: Python :: 3.11
Classifier: Programming Language :: Python :: 3.12
Classifier: Programming Language :: Python :: 3.13
Classifier: Programming Language :: Python :: 3.14
Classifier: Topic :: Software Development :: Libraries :: Python Modules
Requires-Python: <3.15,>=3.8
License-File: LICENSE
Requires-Dist: prettytable>=3.0.0
Requires-Dist: python-dotenv>=0.19.0
Requires-Dist: pyyaml>=6.0
Requires-Dist: tomli>=2.0.0; python_version < "3.11"
Provides-Extra: etcd
Requires-Dist: etcd3>=0.1.5; extra == "etcd"
Provides-Extra: docs
Requires-Dist: sphinx<9.0.0,>=5.0.0; extra == "docs"
Requires-Dist: sphinx-rtd-theme>=1.0.0; extra == "docs"
Requires-Dist: furo>=2024.1.0; extra == "docs"
Requires-Dist: sphinx-autodoc-typehints>=1.19.0; extra == "docs"
Requires-Dist: sphinx-copybutton>=0.5.0; extra == "docs"
Requires-Dist: sphinx-design>=0.5.0; extra == "docs"
Dynamic: license-file
